behave_prophet/colors.py
behave_prophet/prophet_evaluator.py
behave_prophet-0.1.1.dist-info/LICENSE
behave_prophet-0.1.1.dist-info/METADATA
behave_prophet-0.1.1.dist-info/WHEEL
behave_prophet-0.1.1.dist-info/RECORD
